<?xml version="1.0" encoding="utf-8"?>
<XnaContent>
  <Asset Type="FEXNA_Library.Map_Event_Data">
    <Events>
      <Item>
        <name>CastleSE Reinforce</name>
        <trigger>2</trigger>
        <trigger_action>1</trigger_action>
        <trigger_timing>1</trigger_timing>
        <trigger_turn>4</trigger_turn>
        <data>
          <Item>
            <Key>102</Key>
            <Value>
              <Item>On turn 13, 15, 17, etc</Item>
            </Value>
          </Item>
          <Item>
            <Key>201</Key>
            <Value>
              <Item>Turn</Item>
              <Item>13</Item>
              <Item>2</Item>
              <Item>-1</Item>
            </Value>
          </Item>
          <Item>
            <Key>102</Key>
            <Value>
              <Item>Spawn Soldier if clear</Item>
            </Value>
          </Item>
          <Item>
            <Key>201</Key>
            <Value>
              <Item>Tile Occupied-Not</Item>
              <Item>41</Item>
              <Item>21</Item>
            </Value>
          </Item>
          <Item>
            <Key>6</Key>
            <Value>
              <Item>41</Item>
              <Item>21</Item>
              <Item>false</Item>
              <Item>false</Item>
            </Value>
          </Item>
          <Item>
            <Key>12</Key>
            <Value />
          </Item>
          <Item>
            <Key>3</Key>
            <Value>
              <Item>10</Item>
            </Value>
          </Item>
          <Item>
            <Key>201</Key>
            <Value>
              <Item>Turn</Item>
              <Item>15</Item>
              <Item>2</Item>
              <Item>15</Item>
            </Value>
          </Item>
          <Item>
            <Key>21</Key>
            <Value>
              <Item>reinforcement</Item>
              <Item>-1</Item>
              <Item>41</Item>
              <Item>21</Item>
              <Item>12</Item>
            </Value>
          </Item>
          <Item>
            <Key>203</Key>
            <Value />
          </Item>
          <Item>
            <Key>21</Key>
            <Value>
              <Item>reinforcement</Item>
              <Item>-1</Item>
              <Item>41</Item>
              <Item>21</Item>
              <Item>2</Item>
            </Value>
          </Item>
          <Item>
            <Key>204</Key>
            <Value />
          </Item>
          <Item>
            <Key>12</Key>
            <Value />
          </Item>
          <Item>
            <Key>3</Key>
            <Value>
              <Item>10</Item>
            </Value>
          </Item>
          <Item>
            <Key>204</Key>
            <Value />
          </Item>
          <Item>
            <Key>102</Key>
            <Value>
              <Item>End event after turn 17</Item>
            </Value>
          </Item>
          <Item>
            <Key>201</Key>
            <Value>
              <Item>Turn</Item>
              <Item>17</Item>
              <Item>1</Item>
              <Item>-1</Item>
            </Value>
          </Item>
          <Item>
            <Key>250</Key>
            <Value />
          </Item>
          <Item>
            <Key>204</Key>
            <Value />
          </Item>
          <Item>
            <Key>204</Key>
            <Value />
          </Item>
        </data>
      </Item>
      <Item>
        <name>Thief Reinforce</name>
        <trigger>2</trigger>
        <trigger_action>1</trigger_action>
        <trigger_timing>1</trigger_timing>
        <trigger_turn>4</trigger_turn>
        <data>
          <Item>
            <Key>102</Key>
            <Value>
              <Item>On turn 16</Item>
            </Value>
          </Item>
          <Item>
            <Key>201</Key>
            <Value>
              <Item>Turn</Item>
              <Item>16</Item>
              <Item>1</Item>
              <Item>-1</Item>
            </Value>
          </Item>
          <Item>
            <Key>102</Key>
            <Value>
              <Item>Spawn Thief</Item>
            </Value>
          </Item>
          <Item>
            <Key>6</Key>
            <Value>
              <Item>35</Item>
              <Item>26</Item>
              <Item>false</Item>
              <Item>false</Item>
            </Value>
          </Item>
          <Item>
            <Key>12</Key>
            <Value />
          </Item>
          <Item>
            <Key>3</Key>
            <Value>
              <Item>10</Item>
            </Value>
          </Item>
          <Item>
            <Key>21</Key>
            <Value>
              <Item>reinforcement</Item>
              <Item>-1</Item>
              <Item>35</Item>
              <Item>29</Item>
              <Item>10</Item>
            </Value>
          </Item>
          <Item>
            <Key>11</Key>
            <Value>
              <Item>-1</Item>
              <Item>35</Item>
              <Item>26</Item>
            </Value>
          </Item>
          <Item>
            <Key>12</Key>
            <Value />
          </Item>
          <Item>
            <Key>3</Key>
            <Value>
              <Item>10</Item>
            </Value>
          </Item>
          <Item>
            <Key>250</Key>
            <Value />
          </Item>
          <Item>
            <Key>204</Key>
            <Value />
          </Item>
        </data>
      </Item>
      <Item>
        <name>Cohort Reinforce</name>
        <trigger>2</trigger>
        <trigger_action>1</trigger_action>
        <trigger_timing>1</trigger_timing>
        <trigger_turn>4</trigger_turn>
        <data>
          <Item>
            <Key>102</Key>
            <Value>
              <Item>On turn 23</Item>
            </Value>
          </Item>
          <Item>
            <Key>201</Key>
            <Value>
              <Item>Turn</Item>
              <Item>23</Item>
              <Item>1</Item>
              <Item>-1</Item>
            </Value>
          </Item>
          <Item>
            <Key>102</Key>
            <Value>
              <Item>Spawn Cohorts</Item>
            </Value>
          </Item>
          <Item>
            <Key>6</Key>
            <Value>
              <Item>37</Item>
              <Item>2</Item>
              <Item>false</Item>
              <Item>false</Item>
            </Value>
          </Item>
          <Item>
            <Key>12</Key>
            <Value />
          </Item>
          <Item>
            <Key>3</Key>
            <Value>
              <Item>10</Item>
            </Value>
          </Item>
          <Item>
            <Key>21</Key>
            <Value>
              <Item>reinforcement</Item>
              <Item>-1</Item>
              <Item>36</Item>
              <Item>-1</Item>
              <Item>3</Item>
            </Value>
          </Item>
          <Item>
            <Key>11</Key>
            <Value>
              <Item>-1</Item>
              <Item>36</Item>
              <Item>2</Item>
            </Value>
          </Item>
          <Item>
            <Key>21</Key>
            <Value>
              <Item>reinforcement</Item>
              <Item>-1</Item>
              <Item>37</Item>
              <Item>-1</Item>
              <Item>3</Item>
            </Value>
          </Item>
          <Item>
            <Key>11</Key>
            <Value>
              <Item>-1</Item>
              <Item>37</Item>
              <Item>2</Item>
            </Value>
          </Item>
          <Item>
            <Key>21</Key>
            <Value>
              <Item>reinforcement</Item>
              <Item>-1</Item>
              <Item>38</Item>
              <Item>-1</Item>
              <Item>3</Item>
            </Value>
          </Item>
          <Item>
            <Key>11</Key>
            <Value>
              <Item>-1</Item>
              <Item>38</Item>
              <Item>2</Item>
            </Value>
          </Item>
          <Item>
            <Key>12</Key>
            <Value />
          </Item>
          <Item>
            <Key>3</Key>
            <Value>
              <Item>10</Item>
            </Value>
          </Item>
          <Item>
            <Key>250</Key>
            <Value />
          </Item>
          <Item>
            <Key>204</Key>
            <Value />
          </Item>
        </data>
      </Item>
      <Item>
        <name>North Thief Go</name>
        <trigger>2</trigger>
        <trigger_action>1</trigger_action>
        <trigger_timing>1</trigger_timing>
        <trigger_turn>1</trigger_turn>
        <data>
          <Item>
            <Key>102</Key>
            <Value>
              <Item>On turn 26</Item>
            </Value>
          </Item>
          <Item>
            <Key>201</Key>
            <Value>
              <Item>Turn</Item>
              <Item>26</Item>
              <Item>1</Item>
              <Item>-1</Item>
            </Value>
          </Item>
          <Item>
            <Key>202</Key>
            <Value>
              <Item>Team Area</Item>
              <Item>20</Item>
              <Item>2</Item>
              <Item>41</Item>
              <Item>7</Item>
              <Item>PlayerId</Item>
            </Value>
          </Item>
          <Item>
            <Key>22</Key>
            <Value>
              <Item>NorthThief</Item>
              <Item>305</Item>
            </Value>
          </Item>
          <Item>
            <Key>250</Key>
            <Value />
          </Item>
          <Item>
            <Key>204</Key>
            <Value />
          </Item>
        </data>
      </Item>
      <Item>
        <name>CastleCenter Go</name>
        <trigger>2</trigger>
        <trigger_action>1</trigger_action>
        <trigger_timing>1</trigger_timing>
        <trigger_turn>1</trigger_turn>
        <data>
          <Item>
            <Key>102</Key>
            <Value>
              <Item>If north door is opened</Item>
            </Value>
          </Item>
          <Item>
            <Key>201</Key>
            <Value>
              <Item>Door Exists-Not</Item>
              <Item>30</Item>
              <Item>5</Item>
            </Value>
          </Item>
          <Item>
            <Key>22</Key>
            <Value>
              <Item>Group2Soldier1</Item>
              <Item>3</Item>
            </Value>
          </Item>
          <Item>
            <Key>22</Key>
            <Value>
              <Item>Group2Soldier2</Item>
              <Item>3</Item>
            </Value>
          </Item>
          <Item>
            <Key>22</Key>
            <Value>
              <Item>Group2Monk</Item>
              <Item>3</Item>
            </Value>
          </Item>
          <Item>
            <Key>22</Key>
            <Value>
              <Item>Group2Merc</Item>
              <Item>3</Item>
            </Value>
          </Item>
          <Item>
            <Key>22</Key>
            <Value>
              <Item>Group2Soldier3</Item>
              <Item>3</Item>
            </Value>
          </Item>
          <Item>
            <Key>22</Key>
            <Value>
              <Item>Group2Longbow</Item>
              <Item>3</Item>
            </Value>
          </Item>
          <Item>
            <Key>111</Key>
            <Value>
              <Item>1</Item>
              <Item>Set</Item>
              <Item>true</Item>
            </Value>
          </Item>
          <Item>
            <Key>112</Key>
            <Value>
              <Item>4</Item>
              <Item>Turn</Item>
              <Item>0</Item>
            </Value>
          </Item>
          <Item>
            <Key>250</Key>
            <Value />
          </Item>
          <Item>
            <Key>204</Key>
            <Value />
          </Item>
        </data>
      </Item>
    </Events>
  </Asset>
</XnaContent>